{
	"videos": [
		{
			"id": 1,
			"name": "[MyGap] - Феминизм как Сверхценная Идея",
			"author": "MyGap",
			"link": "https://www.youtube.com/watch?v=HaAIo7DZgYI"
		},
		{
			"id": 2,
			"name": "Продал БМВ Х5 и купил баксы. Цели Сергея Мавроди (АО МММ). «компании-зомби».",
			"author": "ДЕНЬГИ 2.0",
			"link": "https://www.youtube.com/watch?v=DMzz6xyhnAM"
		},
		{
			"id": 3,
			"name": "Как Apple докатились от iPod до AirPods Max и полный тест AirPods Max",
			"author": "PRO Hi-Tech",
			"link": "https://www.youtube.com/watch?v=cHfCwcsVagU"
		},
		{
			"id": 4,
			"name": "NO PC, NO PROBLEM - C# and Unity with Boris",
			"author": "Life of Boris",
			"link": "https://www.youtube.com/watch?v=ORboQjn1yAg"
		},
		{
			"id": 5,
			"name": "Капитализм, которого нет",
			"author": "Держать курс",
			"link": "https://www.youtube.com/watch?v=ozCLRhFWdoA"
		},
		{
			"id": 6,
			"name": "[GapNews] Борьба за вакцинатора, гору Куштау, доходы Эпл",
			"author": "MyGap",
			"link": "https://www.youtube.com/watch?v=2pOBHGgG2jY"
		},
		{
			"id": 7,
			"name": "Деревянная мебель в пробирке, искусственная роговица, карта коричневых карликов. Новости QWERTY №156",
			"author": "QWERTY",
			"link": "https://www.youtube.com/watch?v=sSG9U2X5h_4"
		},
		{
			"id": 8,
			"name": "Дворец Путина в Minecraft 1 к 1",
			"author": "TeamCIS [Build The Earth]",
			"link": "https://www.youtube.com/watch?v=jK0t5umHRY4"
		},
		{
			"id": 9,
			"name": "Как НА САМОМ ДЕЛЕ работает нейросеть?",
			"author": "Droider.Ru",
			"link": "https://www.youtube.com/watch?v=WIttZGQEdas"
		},
		{
			"id": 10,
			"name": "Kerbal Space Program 2 Cinematic Announce Trailer",
			"author": "Kerbal Space Program",
			"link": "https://www.youtube.com/watch?v=P_nj6wW6Gsc"
		},
		{
			"id": 11,
			"name": "[MyGap] - Почему женщины постоянно опаздывают",
			"author": "MyGap",
			"link": "https://www.youtube.com/watch?v=PIxdyQ4d7XU"
		},
		{
			"id": 12,
			"name": "Безграничная память. Как запоминать информацию",
			"author": "Простая Академия",
			"link": "https://www.youtube.com/watch?v=diEkFaHklJ0"
		},
		{
			"id": 13,
			"name": "№69 Инвестиционный портфель. Акции США. ETF. ИИС. ВТБ инвестиции. Дивиденды. ОФЗ. Инвестиции 2021.",
			"author": "Финансовая Независимость",
			"link": "https://www.youtube.com/watch?v=oiebqF2Zqdk"
		},
		{
			"id": 14,
			"name": "Это худший смартфон в истории человечества!",
			"author": "Ай, Как Просто!",
			"link": "https://www.youtube.com/watch?v=ybR_f5uII4Y"
		},
		{
			"id": 15,
			"name": "Ниндзя: Подлинная История",
			"author": "АРХИВАРИУС",
			"link": "https://www.youtube.com/watch?v=HxDAMKtV-4I"
		},
		{
			"id": 16,
			"name": "РОССИЙСКИЕ IT-РАЗРАБОТКИ [netstalkers]",
			"author": "netstalkers",
			"link": "https://www.youtube.com/watch?v=WONpEwJmeIk&t=443s"
		},
		{
			"id": 17,
			"name": "Превращаем старый комп в сетевое хранилище с ОС FreeNAS.",
			"author": "PRO Hi-Tech",
			"link": "https://www.youtube.com/watch?v=Hc7Mu6HqABY"
		},
		{
			"id": 18,
			"name": "Извините за просвещение, я не специально",
			"author": "Ёжик Лисичкин",
			"link": "https://www.youtube.com/watch?v=iSAM4rCD7Lo"
		},
		{
			"id": 19,
			"name": "Узбекистан vs Россия - ВВП, зарплата, пенсия, нефть, газ, золото, армия, рождаемость",
			"author": "Uzbek",
			"link": "https://www.youtube.com/watch?v=o9VCqxsnId4"
		}
	]
}