{
	"videos": [
		{
			"id": 1,
			"name": "8 Вещей, Которые Нужно Знать О Крипте Летом 2018. Деньги 2.0",
			"author": "ДЕНЬГИ 2.0",
			"link": "https://www.youtube.com/watch?v=Lr8QbEVw-zc"
		},
		{
			"id": 2,
			"name": "ИСКУССТВЕННЫЕ ПРОБКИ В GOOGLE и ЯНДЕКС картах | Yandex & Google Maps Hacks by overbafer1",
			"author": "overbafer1",
			"link": "https://www.youtube.com/watch?v=vur2yxQUFYY"
		},
		{
			"id": 3,
			"name": "Huawei Kirin – обман или хорошие процессоры? / Huawei против Apple и Qualcomm!",
			"author": "Ай, Как Просто!",
			"link": "https://www.youtube.com/watch?v=8Nxdi421zMw"
		},
		{
			"id": 4,
			"name": "Будет падать всё: рубль, нефть, золото, акции",
			"author": "Деньги не спят",
			"link": "https://www.youtube.com/watch?v=dMzEAXt71tE"
		},
		{
			"id": 5,
			"name": "Чему я Научился у Роберта Кийосаки. Книга «Богатый Папа Бедный Папа».",
			"author": "ДЕНЬГИ 2.0",
			"link": "https://www.youtube.com/watch?v=X1m3QyVR1gw"
		},
		{
			"id": 6,
			"name": "Адель Гадельшин - хитрый коуч / Разоблачение бесплатного тренинга по созданию сайтов / Отзывы",
			"author": "Дмитрий Костин",
			"link": "https://www.youtube.com/watch?v=Ruhoubywfg8"
		},
		{
			"id": 7,
			"name": "HDMI 2.1 — ОБЪЯСНЯЕМ ТЕХНОЛОГИИ",
			"author": "Droider.Ru",
			"link": "https://www.youtube.com/watch?v=cWz8lKlTkmY"
		},
		{
			"id": 8,
			"name": "ТОП-10. Истории года, по которым нужно снять фильм.",
			"author": "Кино Огонь",
			"link": "https://www.youtube.com/watch?v=7mWVKt6qp2o"
		},
		{
			"id": 9,
			"name": "В мире животных №1.Зашквар Reebok, Рыбка Дерипаско, Сломанные Ребра Гуфа, уфимские жлобы",
			"author": "ДЕНЬГИ 2.0",
			"link": "https://www.youtube.com/watch?v=cgG_4u1SOa8"
		},
		{
			"id": 10,
			"name": "RESTful API With PHP & MySQL",
			"author": "Traversy Media",
			"link": "https://www.youtube.com/watch?v=DHUxnUX7Y2Y"
		},
		{
			"id": 11,
			"name": "ТУТОРИАЛ №2. Как Продать БИТКОИН и Вывести Деньги Из Крипты в РФ и УКР.",
			"author": "ДЕНЬГИ 2.0",
			"link": "https://www.youtube.com/watch?v=A0CJqhKPNig"
		},
		{
			"id": 12,
			"name": "Акция 23 января в поддержку Навального. Итоги",
			"author": "Телеканал Дождь",
			"link": "https://www.youtube.com/watch?v=3SECESZWQHY"
		},
		{
			"id": 13,
			"name": "KSP UNDERWATER BASE",
			"author": "Gordon's workshop",
			"link": "https://www.youtube.com/watch?v=5uPMcEdA5wc"
		},
		{
			"id": 14,
			"name": "Приключения Электроника (1979)",
			"author": "Золотая коллекция русского кино",
			"link": "https://www.youtube.com/watch?v=kmKYL7wT5C4"
		},
		{
			"id": 15,
			"name": "Астрообзор #25 / Взвесить Млечный Путь / Затмение замерло / Лунный грунт / Superbolide на фото",
			"author": "Космос Просто",
			"link": "https://www.youtube.com/watch?v=NOXql2uG8Lk"
		},
		{
			"id": 16,
			"name": "КАК ЧИТАТЬ С УМОМ. Простые, но важные советы",
			"author": "Простая Академия",
			"link": "https://www.youtube.com/watch?v=yZn2SES_Lek"
		},
		{
			"id": 17,
			"name": "СТАС АЙ КАК ПРОСТО ОБСУЖДЕНИЕ ПРОДЮСЕРА ИВАНОВА С Itpedia, ШТУРМ КАПИТОЛИЯ, НАВАЛЬНЫЙ // СТАСLIVE",
			"author": "СТРИМЫ СТАСА АЙ, КАК ПРОСТО!",
			"link": "https://www.youtube.com/watch?v=hzXBMwSEiaA"
		}
	]
}