{
	"videos": [
		{
			"id": 1,
			"name": "KSP Build Fly Dream Trailer",
			"author": "Shaun Esau",
			"link": "https://www.youtube.com/watch?v=RkDOOsGg-9I"
		},
		{
			"id": 2,
			"name": "Почему дыра важна // Напечатали сердце // Чо там на Украине // Деньги богатеев",
			"author": "MyGap",
			"link": "https://www.youtube.com/watch?v=FjcAtg7iVmo"
		},
		{
			"id": 3,
			"name": "«Дворец Путина» | Разбор архитектуры резиденции в Геленджике",
			"author": "Евгений Урих",
			"link": "https://www.youtube.com/watch?v=c3L_wA5wJmI"
		},
		{
			"id": 4,
			"name": "Как Сохранять Мотивацию (Правило Локуса Контроля)",
			"author": "Таблетка Саморазвития",
			"link": "https://www.youtube.com/watch?v=qBGdMTOET1Q"
		},
		{
			"id": 5,
			"name": "ВИДЕОКАРТА APPLE // SONY УБИВАЕТ PLAYSTATION! - ОСТАНОВИТЕСЬ!!! // HUAWEI ПОКУПАЕТ РОССИЮ",
			"author": "iKakProsto2",
			"link": "https://www.youtube.com/watch?v=MP7AslCJ2pk"
		},
		{
			"id": 6,
			"name": "Глубокое программирование музыки - Навыки программирования - Ночная работа Chillstep",
			"author": "Music Lab",
			"link": "https://www.youtube.com/watch?v=FuaQ1QhJOkc"
		},
		{
			"id": 7,
			"name": "Уоррен Баффет - Интервью 2020! Что будет с акциями? Советы Миллиардера!",
			"author": "INSTARDING",
			"link": "https://www.youtube.com/watch?v=2nBtKKy7dWI"
		},
		{
			"id": 8,
			"name": "ТУТОРИАЛ №2. Как Продать БИТКОИН и Вывести Деньги Из Крипты в РФ и УКР.",
			"author": "ДЕНЬГИ 2.0",
			"link": "https://www.youtube.com/watch?v=A0CJqhKPNig"
		},
		{
			"id": 9,
			"name": "[MyGap] - Великая депрессия: расцвет культуры потребления",
			"author": "MyGap",
			"link": "https://www.youtube.com/watch?v=8qBdegWRc_M"
		},
		{
			"id": 10,
			"name": "Elon Musk's Insane Idea to Get 1 Million People on Mars by 2050",
			"author": "RealLifeLore",
			"link": "https://www.youtube.com/watch?v=bjnmLa16rIo"
		},
		{
			"id": 11,
			"name": "Сбербанк Инвестор: честный обзор приложения 2021 / Инвестиции в акции через Сбербанк: плюсы и минусы",
			"author": "InvestFuture",
			"link": "https://www.youtube.com/watch?v=Bg2P-KAdHTo"
		},
		{
			"id": 12,
			"name": "Самый БОЛЬШОЙ ПРОЦЕССОР в мире! РАЗБОР",
			"author": "Droider.Ru",
			"link": "https://www.youtube.com/watch?v=vd3vDRkcC7w"
		},
		{
			"id": 13,
			"name": "KSP: 54-wheeled LAND TRAIN to Duna!",
			"author": "Matt Lowne",
			"link": "https://www.youtube.com/watch?v=wPPh5LBbI7g"
		},
		{
			"id": 14,
			"name": "ЧТО ДЕЛАТЬ ЕСЛИ ПОПАЛ В ПРОШЛОЕ",
			"author": "ДЕНЬГИ 2.0",
			"link": "https://www.youtube.com/watch?v=JMZLh6YrY8E"
		}
	]
}