{
	"videos": [
		{
			"id": 1,
			"name": "ВОЛЯ. Этот сюжет поменяет твою жизнь.",
			"author": "ДЕНЬГИ 2.0",
			"link": "https://www.youtube.com/watch?v=Q6UfTFq4ja0"
		},
		{
			"id": 2,
			"name": "КАК работает ЭЛТ Монитор: ЗАЧЕМ в 2020?",
			"author": "Droider.Ru",
			"link": "https://www.youtube.com/watch?v=ghEIkYzr8Qo"
		},
		{
			"id": 3,
			"name": "React + NodeJS Сайт за 3 часа с нуля",
			"author": "Владилен Минин",
			"link": "https://www.youtube.com/watch?v=ivDjWYcKDZI"
		},
		{
			"id": 4,
			"name": "KSP: 54-wheeled LAND TRAIN to Duna!",
			"author": "Matt Lowne",
			"link": "https://www.youtube.com/watch?v=wPPh5LBbI7g"
		},
		{
			"id": 5,
			"name": "Ленивый Способ Разбогатеть На AMAZON = 5 Простых Шагов.",
			"author": "ДЕНЬГИ 2.0",
			"link": "https://www.youtube.com/watch?v=fINuaSHPztA"
		},
		{
			"id": 6,
			"name": "Светочи с Аliexpress",
			"author": "Lisin YT",
			"link": "https://www.youtube.com/watch?v=F8dI1j7y_Rs"
		},
		{
			"id": 7,
			"name": "Метаболизм (1 часть из 4)| Рост и обмен веществ | Медицина",
			"author": "KhanAcademyRussian",
			"link": "https://www.youtube.com/watch?v=Tl3aHUNd-fM"
		},
		{
			"id": 8,
			"name": "РАЗОБЛАЧЕНИЕ: продажные itpedia и Стас Ай Как Просто!",
			"author": "Ай, Как Просто!",
			"link": "https://www.youtube.com/watch?v=AcdNcLhU1lg"
		},
		{
			"id": 9,
			"name": "11 ФУНКЦИЙ Android 11, которых НЕТ",
			"author": "Droider.Ru",
			"link": "https://www.youtube.com/watch?v=xW6XNMZvm4M"
		},
		{
			"id": 10,
			"name": "В БЕЛУЮ РОЩУ БЕЗ МАШИНЫ ► HALF-LIFE 2: Episode Two",
			"author": "STALKEROS",
			"link": "https://www.youtube.com/watch?v=lF_XDBzuMNo"
		},
		{
			"id": 11,
			"name": "КАК МОНЕТИЗИРОВАТЬ УЖАС: Бизнес На Страхе и Мертвецах.",
			"author": "ДЕНЬГИ 2.0",
			"link": "https://www.youtube.com/watch?v=CW76bOOpiG0"
		},
		{
			"id": 12,
			"name": "The Future of Design",
			"author": "SpaceX",
			"link": "https://www.youtube.com/watch?v=xNqs_S-zEBY"
		},
		{
			"id": 13,
			"name": "Будет падать всё: рубль, нефть, золото, акции",
			"author": "Деньги не спят",
			"link": "https://www.youtube.com/watch?v=dMzEAXt71tE"
		},
		{
			"id": 14,
			"name": "Как Джим Керри стал «королем комедии» и почему перестал шутить",
			"author": "КиноПоиск",
			"link": "https://www.youtube.com/watch?v=V0JKhFjKm6M"
		},
		{
			"id": 15,
			"name": "КАК ЧИТАТЬ С УМОМ. Простые, но важные советы",
			"author": "Простая Академия",
			"link": "https://www.youtube.com/watch?v=yZn2SES_Lek"
		},
		{
			"id": 16,
			"name": "Linux Mint 20.1 «Ulyssa»",
			"author": "Pingvinus",
			"link": "https://www.youtube.com/watch?v=mzIinmLu1qU"
		},
		{
			"id": 17,
			"name": "Ну в этот раз инопланетяне? Сигналы от двух планет / Астрообзор #71",
			"author": "Космос Просто",
			"link": "https://www.youtube.com/watch?v=LBGYabXVAhA"
		}
	]
}