{
	"videos": [
		{
			"id": 1,
			"name": "ЧТО НЕ ДЕЛАЮТ МИЛЛИОНЕРЫ",
			"author": "ДЕНЬГИ 2.0",
			"link": "https://www.youtube.com/watch?v=JAA1OQXqtrs"
		},
		{
			"id": 2,
			"name": "Обход родительского контроля на ПК",
			"author": "overbafer1",
			"link": "https://www.youtube.com/watch?v=LLKjFTVgZnI"
		},
		{
			"id": 3,
			"name": "В БЕЛУЮ РОЩУ БЕЗ МАШИНЫ ► HALF-LIFE 2: Episode Two",
			"author": "STALKEROS",
			"link": "https://www.youtube.com/watch?v=lF_XDBzuMNo"
		},
		{
			"id": 4,
			"name": "Интервью Илона Маск на конференции Satellite 2020 |На русском| (09.03.2020)",
			"author": "Илон Маск",
			"link": "https://www.youtube.com/watch?v=gvcsELHmzgg"
		},
		{
			"id": 5,
			"name": "5 Убийц ТВОЕЙ Уверенности в Себе",
			"author": "ДЕНЬГИ 2.0",
			"link": "https://www.youtube.com/watch?v=UkEoxuAH1YA"
		},
		{
			"id": 6,
			"name": "Build A Simple Android App With Kotlin",
			"author": "Traversy Media",
			"link": "https://www.youtube.com/watch?v=BBWyXo-3JGQ"
		},
		{
			"id": 7,
			"name": "Разбор тестового задания на вакансию Junior Frontend Developer",
			"author": "Hi Pro!",
			"link": "https://www.youtube.com/watch?v=x9V9K13n00g"
		},
		{
			"id": 8,
			"name": "Миллиардер о Митинге 23 января | Протест ничего не изменит в России? Путин и Навальный.",
			"author": "Игорь Рыбаков",
			"link": "https://www.youtube.com/watch?v=sYisFKiKQI0"
		},
		{
			"id": 9,
			"name": "10 заповедей по пайке. Учимся паять",
			"author": "AmperkaRu",
			"link": "https://www.youtube.com/watch?v=abegqxwXOAY"
		},
		{
			"id": 10,
			"name": "СХЕМАТОЗ от ДЕНЧИКА. INET-БАБЛО = Pinterest + POD (teespring.com).",
			"author": "ДЕНЬГИ 2.0",
			"link": "https://www.youtube.com/watch?v=MLHvm42skxQ"
		},
		{
			"id": 11,
			"name": "Doom E1M1 theme played on musical tesla coil",
			"author": "Vilho Ranto",
			"link": "https://www.youtube.com/watch?v=aDBhdPNEKDU"
		},
		{
			"id": 12,
			"name": "Elegant API Versioning in ASP.NET Core (Web API)",
			"author": "Nick Chapsas",
			"link": "https://www.youtube.com/watch?v=iVHtKG0eU_s"
		},
		{
			"id": 13,
			"name": "iPHONE 12 ВСЕ // GOOGLE ОПЯТЬ ВСЁ СЛОМАЛИ // HARMONY OS УЖЕ ТУТ",
			"author": "iKakProsto2",
			"link": "https://www.youtube.com/watch?v=IP2P1YsH8DA"
		},
		{
			"id": 14,
			"name": "ОТКУДА появились АРТРОПОДЫ (Часть №1) | ЭВОЛЮЦИЯ АРТРОПОД | Онихофоры | Аномалокарис | Тихоходка",
			"author": "Упоротый Палеонтолог",
			"link": "https://www.youtube.com/watch?v=eJh36Axuvms"
		},
		{
			"id": 15,
			"name": "Без этого жизни на Земле не было бы / Космос",
			"author": "Космос Просто",
			"link": "https://www.youtube.com/watch?v=N15iDGI-XK0"
		},
		{
			"id": 16,
			"name": "Извините за просвещение, я не специально",
			"author": "Ёжик Лисичкин",
			"link": "https://www.youtube.com/watch?v=iSAM4rCD7Lo"
		},
		{
			"id": 17,
			"name": "Крипта, блокчейн и два биткоина: что было, есть и куда мы катимся",
			"author": "MyGap",
			"link": "https://www.youtube.com/watch?v=tLDdMFjP_NE"
		}
	]
}