{
	"videos": [
		{
			"id": 1,
			"name": "Образование в Чехии. Как потерять деньги и год жизни?",
			"author": "Игорь Линк",
			"link": "https://www.youtube.com/watch?v=c7JA3fxLjUo"
		},
		{
			"id": 2,
			"name": "Бытовой Торчок. ДЕНЬГИ 2.0",
			"author": "ДЕНЬГИ 2.0",
			"link": "https://www.youtube.com/watch?v=aQHupYegcSM"
		},
		{
			"id": 3,
			"name": "Лжецелитель Аркадий Петров: исцеление, восстановление органов и воскрешение (МРАКОБЕСИЕ #3)",
			"author": "Дмитрий Костин",
			"link": "https://www.youtube.com/watch?v=kdhdwde1U6w"
		},
		{
			"id": 4,
			"name": "Подготовка к JavaScript собеседованию",
			"author": "Владилен Минин",
			"link": "https://www.youtube.com/watch?v=M_pclb-58ZY"
		},
		{
			"id": 5,
			"name": "ХОЧЕШЬ? - ДЕЛАЙ!!! (Денис борисов)",
			"author": "PERFECT PHYSIQUE",
			"link": "https://www.youtube.com/watch?v=euarhVpUo2g"
		},
		{
			"id": 6,
			"name": "САМЫЕ ЗАХВАТЫВАЮЩИЕ КНИГИ📖Книги, от которых невозможно оторваться",
			"author": "MyBook",
			"link": "https://www.youtube.com/watch?v=UFfvBnJ-QtY"
		},
		{
			"id": 7,
			"name": "СТАС АЙ КАК ПРОСТО ОБСУЖДЕНИЕ ПРОДЮСЕРА ИВАНОВА С Itpedia, ШТУРМ КАПИТОЛИЯ, НАВАЛЬНЫЙ // СТАСLIVE",
			"author": "СТРИМЫ СТАСА АЙ, КАК ПРОСТО!",
			"link": "https://www.youtube.com/watch?v=hzXBMwSEiaA"
		},
		{
			"id": 8,
			"name": "Стальной Гигант, или как Голливуд снова все испортил",
			"author": "Культас",
			"link": "https://www.youtube.com/watch?v=i1hemy6LLWw"
		},
		{
			"id": 9,
			"name": "О Чем Никогда НЕ расскажет Бизнес-Тренер",
			"author": "ДЕНЬГИ 2.0",
			"link": "https://www.youtube.com/watch?v=PPfn5GS6beQ"
		},
		{
			"id": 10,
			"name": "ЛЮБЛЮ ЭКРАН СМЕРТИ или КУПИЛ КОМПЬЮТЕР НА ALIEXPRESS - МИСТИЧЕСКИЙ ПК и BSOD",
			"author": "overbafer1",
			"link": "https://www.youtube.com/watch?v=pJKrf_VKHqY"
		},
		{
			"id": 11,
			"name": "Как делаются деньги. Когда доллар по 100 руб. Зачем нам грязные зеленые бумажки.",
			"author": "ДЕНЬГИ 2.0",
			"link": "https://www.youtube.com/watch?v=Qv1kwLKdMAs&t=39s"
		},
		{
			"id": 12,
			"name": "Цикады не плачут: CICADA 3301. Часть 1",
			"author": "FlynnFlyTaggart",
			"link": "https://www.youtube.com/watch?v=w5XlQk41AUg"
		},
		{
			"id": 13,
			"name": "Кремниевые Титаны #33: Adobe Flash",
			"author": "Дмитрий Бачило",
			"link": "https://www.youtube.com/watch?v=n36SBtx0-rU"
		},
		{
			"id": 14,
			"name": "Российский рынок на пороге санкций. Еврозону ждет рецессия / Новости рынков",
			"author": "InvestFuture",
			"link": "https://www.youtube.com/watch?v=oCGwADv9ibc"
		},
		{
			"id": 15,
			"name": "Дефицит автомобилей, одуревшие дилеры – а виной всему потребительская электроника.",
			"author": "PRO Hi-Tech",
			"link": "https://www.youtube.com/watch?v=-KlwGvFhQWk"
		},
		{
			"id": 16,
			"name": "HTML и CSS с нуля для начинающих | 🔥 Быстрый Старт!",
			"author": "BrainsCloud",
			"link": "https://www.youtube.com/watch?v=CvEttNvty0U"
		},
		{
			"id": 17,
			"name": "Большой куш, Гай Ричи, сессия (Переозвучка)",
			"author": "TheNafig",
			"link": "https://www.youtube.com/watch?v=1KMF6Vj0qq0"
		}
	]
}